helm_charts/__init__.py
helm_charts/helm_functions.py
helm_charts/helper.py
helm_charts/init_checks.py
helm_charts/k8s_charts_installer.py
helm_charts/k8s_charts_installer_unittest.py
helm_charts/kubectl_functions.py
helm_charts/menu_create_namespace.py
helm_charts/menu_delete_charts.py
helm_charts/menu_delete_namespace.py
helm_charts/menu_delete_repos.py
helm_charts/menu_install_charts.py
helm_charts/menu_install_repo.py
helm_charts/values_files/airflow.values.local.yml
helm_charts/values_files/ingress-traefik.values.local.yml
helm_charts/values_files/jenkins.configmap.yml
helm_charts/values_files/jenkins.values.local.yml
helm_charts/values_files/kubernetes-dashboard.values.local.yml
helm_charts/values_files/mysql.values.local.yml
helm_charts/values_files/nalkinscloud.api.values.local.yml
helm_charts/values_files/nalkinscloud.frontend.values.local.yml
helm_charts/values_files/openfaas.values.local.yml
helm_charts/values_files/rabbitmq.values.local.yml
helm_charts/values_files/redis.values.local.yml
helm_charts-1.0.16.dist-info/LICENSE
helm_charts-1.0.16.dist-info/METADATA
helm_charts-1.0.16.dist-info/WHEEL
helm_charts-1.0.16.dist-info/entry_points.txt
helm_charts-1.0.16.dist-info/top_level.txt
helm_charts-1.0.16.dist-info/RECORD
