Metadata-Version: 2.1
Name: helm-charts
Version: 1.0.16
Summary: Helm Charts installer
Home-page: https://github.com/ArieLevs/Helm-Charts-Installer
Author: Arie Lev
Author-email: levinsonarie@gmail.com
License: Apache License 2.0
Platform: UNKNOWN
Classifier: Programming Language :: Python :: 3
Classifier: Programming Language :: Python :: 3.5
Classifier: Programming Language :: Python :: 3.6
Classifier: License :: OSI Approved :: Apache Software License
Classifier: Operating System :: Unix
Classifier: Operating System :: MacOS
